airflow_anomaly_detection/__init__.py
airflow_anomaly_detection/utils.py
airflow_anomaly_detection/example_dags/__init__.py
airflow_anomaly_detection/example_dags/bigquery_anomaly_detection_dag/__init__.py
airflow_anomaly_detection/example_dags/bigquery_anomaly_detection_dag/bigquery_anomaly_detection_dag.py
airflow_anomaly_detection/operators/__init__.py
airflow_anomaly_detection/operators/metric_batch_email_notify_operator.py
airflow_anomaly_detection/operators/bigquery/metric_batch_alert_operator.py
airflow_anomaly_detection/operators/bigquery/metric_batch_ingest_operator.py
airflow_anomaly_detection/operators/bigquery/metric_batch_score_operator.py
airflow_anomaly_detection/operators/bigquery/metric_batch_train_operator.py
airflow_provider_anomaly_detection-0.0.33.dist-info/METADATA
airflow_provider_anomaly_detection-0.0.33.dist-info/WHEEL
airflow_provider_anomaly_detection-0.0.33.dist-info/licenses/LICENSE
airflow_provider_anomaly_detection-0.0.33.dist-info/RECORD
