Metadata-Version: 2.1
Name: airflow-provider-anomaly-detection
Version: 0.0.33
Summary: An airflow provider for anomaly detection.
Project-URL: Homepage, https://github.com/andrewm4894/airflow-provider-anomaly-detection
Project-URL: Bug Tracker, https://github.com/andrewm4894/airflow-provider-anomaly-detection/issues
Author-email: andrewm4894 <andrewm4894@gmail.com>
License-File: LICENSE
Classifier: Framework :: Apache Airflow
Classifier: Framework :: Apache Airflow :: Provider
Requires-Python: >=3.7
